README.rst
setup.py
Sens.egg-info/PKG-INFO
Sens.egg-info/SOURCES.txt
Sens.egg-info/dependency_links.txt
Sens.egg-info/entry_points.txt
Sens.egg-info/requires.txt
Sens.egg-info/top_level.txt
Sens.egg-info/zip-safe
sens/__init__.py
sens/__main__.py
sens/application.py
sens/image.py
sens/status.py