Metadata-Version: 1.0
Name: Sens
Version: 0.0.3
Summary: A dynamic Twitch status image generator
Home-page: https://github.com/TronPaul/sens
Author: Mark McGuire
Author-email: ???
License: UNKNOWN
Platform: UNKNOWN
